pixelscan/__init__.py
pixelscan/pixelscan.py
pixelscan-0.4.6.dist-info/LICENSE.TXT
pixelscan-0.4.6.dist-info/METADATA
pixelscan-0.4.6.dist-info/WHEEL
pixelscan-0.4.6.dist-info/top_level.txt
pixelscan-0.4.6.dist-info/RECORD
