Metadata-Version: 2.1
Name: pixelscan
Version: 0.4.6
Summary: A library to scan pixels on a grid in a variety of patterns.
Home-page: https://github.com/dpmcmlxxvi/pixelscan
Author: Daniel Pulido
Author-email: dpmcmlxxvi@gmail.com
License: MIT
Download-URL: https://github.com/dpmcmlxxvi/pixelscan/tarball/v0.4.6
